namespace/__init__.py
namespace/_namespace.py
python_namespace-1.0.dist-info/LICENSE
python_namespace-1.0.dist-info/METADATA
python_namespace-1.0.dist-info/WHEEL
python_namespace-1.0.dist-info/top_level.txt
python_namespace-1.0.dist-info/RECORD
