Metadata-Version: 2.1
Name: python-namespace
Version: 1.0
Summary: Namespaces for class properties and methods
Home-page: https://github.com/tobiasgehring/python-namespace
Download-URL: https://github.com/tobiasgehring/python-namespace/archive/v1.0.tar.gz
Author: Tobias Gehring
Author-email: tobias.gehring@fysik.dtu.dk
License: LGPLv3
Platform: all
Classifier: Development Status :: 4 - Beta
Classifier: Intended Audience :: Science/Research
Classifier: License :: OSI Approved :: GNU Lesser General Public License v3 (LGPLv3)
Classifier: Programming Language :: Python
Classifier: Topic :: Scientific/Engineering
Classifier: Topic :: Software Development :: Libraries
Classifier: Topic :: System :: Hardware
Classifier: Operating System :: Microsoft :: Windows
License-File: LICENSE
